{
    "Statement": [
        {
            "Action": "iam:CreateServiceLinkedRole",
            "Condition": {
                "StringEquals": {
                    "iam:AWSServiceName": "elasticloadbalancing.amazonaws.com"
                  }
              },
            "Effect": "Allow",
            "Resource": "*",
            "Sid": ""
        },
        {
            "Action": [
                "elasticloadbalancing:DescribeTargetHealth",
                "elasticloadbalancing:DescribeTargetGroups",
                "elasticloadbalancing:DescribeTargetGroupAttributes",
                "elasticloadbalancing:DescribeTags",
                "elasticloadbalancing:DescribeSSLPolicies",
                "elasticloadbalancing:DescribeRules",
                "elasticloadbalancing:DescribeLoadBalancers",
                "elasticloadbalancing:DescribeLoadBalancerAttributes",
                "elasticloadbalancing:DescribeListeners",
                "elasticloadbalancing:DescribeListenerCertificates",
                "ec2:GetCoipPoolUsage",
                "ec2:DescribeVpcs",
                "ec2:DescribeVpcPeeringConnections",
                "ec2:DescribeTags",
                "ec2:DescribeSubnets",
                "ec2:DescribeSecurityGroups",
                "ec2:DescribeNetworkInterfaces",
                "ec2:DescribeInternetGateways",
                "ec2:DescribeInstances",
                "ec2:DescribeCoipPools",
                "ec2:DescribeAvailabilityZones",
                "ec2:DescribeAddresses",
                "ec2:DescribeAccountAttributes"
            ],
            "Effect": "Allow",
            "Resource": "*",
            "Sid": ""
        },
        {
            "Action": [
                "wafv2:GetWebACLForResource",
                "wafv2:GetWebACL",
                "wafv2:DisassociateWebACL",
                "wafv2:AssociateWebACL",
                "waf-regional:GetWebACLForResource",
                "waf-regional:GetWebACL",
                "waf-regional:DisassociateWebACL",
                "waf-regional:AssociateWebACL",
                "shield:GetSubscriptionState",
                "shield:DescribeProtection",
                "shield:DeleteProtection",
                "shield:CreateProtection",
                "iam:ListServerCertificates",
                "iam:GetServerCertificate",
                "cognito-idp:DescribeUserPoolClient",
                "acm:ListCertificates",
                "acm:DescribeCertificate"
            ],
            "Effect": "Allow",
            "Resource": "*",
            "Sid": ""
        },
        {
            "Action": [
                "ec2:RevokeSecurityGroupIngress",
                "ec2:AuthorizeSecurityGroupIngress"
            ],
            "Effect": "Allow",
            "Resource": "*",
            "Sid": ""
        },
        {
            "Action": "ec2:CreateSecurityGroup",
            "Effect": "Allow",
            "Resource": "*",
            "Sid": ""
        },
        {
            "Action": "ec2:CreateTags",
            "Condition": {
                "Null": {
                    "aws:RequestTag/elbv2.k8s.aws/cluster": "false"
                },
                "StringEquals": {
                    "ec2:CreateAction": "CreateSecurityGroup"
                }
            },
            "Effect": "Allow",
            "Resource": "arn:aws:ec2:*:*:security-group/*",
            "Sid": ""
        },
        {
            "Action": [
                "ec2:DeleteTags",
                "ec2:CreateTags"
            ],
            "Condition": {
                "Null": {
                    "aws:ResourceTag/ingress.k8s.aws/cluster": "false"
                  }
            },
            "Effect": "Allow",
            "Resource": "arn:aws:ec2:*:*:security-group/*",
            "Sid": ""
        },
        {
            "Action": [
                "elasticloadbalancing:RemoveTags",
                "elasticloadbalancing:DeleteTargetGroup",
                "elasticloadbalancing:AddTags"
            ],
            "Condition": {
                "Null": {
                    "aws:ResourceTag/ingress.k8s.aws/cluster": "false"
                  }
            },
            "Effect": "Allow",
            "Resource": [
                "arn:aws:elasticloadbalancing:*:*:targetgroup/*/*",
                "arn:aws:elasticloadbalancing:*:*:loadbalancer/net/*/*",
                "arn:aws:elasticloadbalancing:*:*:loadbalancer/app/*/*"
            ],
            "Sid": ""
        },
        {
            "Action": [
                "ec2:DeleteTags",
                "ec2:CreateTags"
            ],
            "Condition": {
                "Null": {
                    "aws:RequestTag/elbv2.k8s.aws/cluster": "true",
                    "aws:ResourceTag/elbv2.k8s.aws/cluster": "false"
                }
            },
            "Effect": "Allow",
            "Resource": "arn:aws:ec2:*:*:security-group/*",
            "Sid": ""
        },
        {
            "Action": [
                "ec2:RevokeSecurityGroupIngress",
                "ec2:DeleteSecurityGroup",
                "ec2:AuthorizeSecurityGroupIngress"
            ],
            "Condition": {
                "Null": {
                    "aws:ResourceTag/elbv2.k8s.aws/cluster": "false"
                  }
            },
            "Effect": "Allow",
            "Resource": "*",
            "Sid": ""
        },
        {
            "Action": [
                "elasticloadbalancing:CreateTargetGroup",
                "elasticloadbalancing:CreateLoadBalancer"
            ],
            "Condition": {
                "Null": {
                    "aws:RequestTag/elbv2.k8s.aws/cluster": "false"
                  }
            },
            "Effect": "Allow",
            "Resource": "*",
            "Sid": ""
        },
        {
            "Action": [
                "elasticloadbalancing:DeleteRule",
                "elasticloadbalancing:DeleteListener",
                "elasticloadbalancing:CreateRule",
                "elasticloadbalancing:CreateListener"
            ],
            "Effect": "Allow",
            "Resource": "*",
            "Sid": ""
        },
        {
            "Action": [
                "elasticloadbalancing:RemoveTags",
                "elasticloadbalancing:AddTags"
            ],
            "Condition": {
                "Null": {
                    "aws:RequestTag/elbv2.k8s.aws/cluster": "true",
                    "aws:ResourceTag/elbv2.k8s.aws/cluster": "false"
                  }
            },
            "Effect": "Allow",
            "Resource": [
                "arn:aws:elasticloadbalancing:*:*:targetgroup/*/*",
                "arn:aws:elasticloadbalancing:*:*:loadbalancer/net/*/*",
                "arn:aws:elasticloadbalancing:*:*:loadbalancer/app/*/*"
            ],
            "Sid": ""
        },
        {
            "Action": [
                "elasticloadbalancing:RemoveTags",
                "elasticloadbalancing:AddTags"
            ],
            "Effect": "Allow",
            "Resource": [
                "arn:aws:elasticloadbalancing:*:*:listener/net/*/*/*",
                "arn:aws:elasticloadbalancing:*:*:listener/app/*/*/*",
                "arn:aws:elasticloadbalancing:*:*:listener-rule/net/*/*/*",
                "arn:aws:elasticloadbalancing:*:*:listener-rule/app/*/*/*"
            ],
            "Sid": ""
        },
        {
            "Action": [
                "elasticloadbalancing:SetSubnets",
                "elasticloadbalancing:SetSecurityGroups",
                "elasticloadbalancing:SetIpAddressType",
                "elasticloadbalancing:ModifyTargetGroupAttributes",
                "elasticloadbalancing:ModifyTargetGroup",
                "elasticloadbalancing:ModifyLoadBalancerAttributes",
                "elasticloadbalancing:DeleteTargetGroup",
                "elasticloadbalancing:DeleteLoadBalancer"
            ],
            "Condition": {
                "Null": {
                    "aws:ResourceTag/elbv2.k8s.aws/cluster": "false"
                  }
            },
            "Effect": "Allow",
            "Resource": "*",
            "Sid": ""
        },
        {
            "Action": [
                "elasticloadbalancing:RegisterTargets",
                "elasticloadbalancing:DeregisterTargets"
            ],
            "Effect": "Allow",
            "Resource": "arn:aws:elasticloadbalancing:*:*:targetgroup/*/*",
            "Sid": ""
        },
        {
            "Action": [
                "elasticloadbalancing:SetWebAcl",
                "elasticloadbalancing:RemoveListenerCertificates",
                "elasticloadbalancing:ModifyRule",
                "elasticloadbalancing:ModifyListener",
                "elasticloadbalancing:AddListenerCertificates"
            ],
            "Effect": "Allow",
            "Resource": "*",
            "Sid": ""
        }
    ],
    "Version": "2012-10-17"
}

